openinference/instrumentation/litellm/__init__.py
openinference/instrumentation/litellm/_responses_attributes.py
openinference/instrumentation/litellm/package.py
openinference/instrumentation/litellm/py.typed
openinference/instrumentation/litellm/version.py
openinference_instrumentation_litellm-0.1.29.dist-info/METADATA
openinference_instrumentation_litellm-0.1.29.dist-info/WHEEL
openinference_instrumentation_litellm-0.1.29.dist-info/entry_points.txt
openinference_instrumentation_litellm-0.1.29.dist-info/licenses/LICENSE
openinference_instrumentation_litellm-0.1.29.dist-info/RECORD
