Metadata-Version: 2.4
Name: openinference-instrumentation-litellm
Version: 0.1.29
Summary: OpenInference liteLLM Instrumentation
Project-URL: Homepage, https://github.com/Arize-ai/openinference/tree/main/python/instrumentation/openinference-instrumentation-litellm
Author-email: OpenInference Authors <oss@arize.com>
License-Expression: Apache-2.0
License-File: LICENSE
Classifier: Development Status :: 5 - Production/Stable
Classifier: Intended Audience :: Developers
Classifier: License :: OSI Approved :: Apache Software License
Classifier: Programming Language :: Python
Classifier: Programming Language :: Python :: 3
Classifier: Programming Language :: Python :: 3.10
Classifier: Programming Language :: Python :: 3.11
Classifier: Programming Language :: Python :: 3.12
Classifier: Programming Language :: Python :: 3.13
Classifier: Programming Language :: Python :: 3.14
Requires-Python: <3.15,>=3.10
Requires-Dist: openinference-instrumentation>=0.1.27
Requires-Dist: openinference-semantic-conventions>=0.1.25
Requires-Dist: opentelemetry-api
Requires-Dist: opentelemetry-instrumentation
Requires-Dist: opentelemetry-sdk
Requires-Dist: setuptools
Requires-Dist: wrapt
Provides-Extra: test
Requires-Dist: fastapi; extra == 'test'
Requires-Dist: litellm; extra == 'test'
Requires-Dist: opentelemetry-instrumentation-httpx; extra == 'test'
Requires-Dist: opentelemetry-sdk; extra == 'test'
Requires-Dist: orjson; extra == 'test'
Requires-Dist: pytest-vcr; extra == 'test'
Requires-Dist: tenacity; extra == 'test'
Requires-Dist: tokenizers==0.20.3; (python_version == '3.8') and extra == 'test'
